{
  "users": [
    {
      "userId": "U001",
      "userName": "rsharma",
      "firstName": "Rohan",
      "lastName": "Sharma",
      "fullName": "Rohan Sharma",
      "email": "rohan.sharma@acme.com",
      "department": "Finance",
      "jobTitle": "AP Accountant",
      "companyCode": "1000",
      "managerId": "U004",
      "managerName": "Priya Malhotra",
      "status": "Active",
      "riskLevel": "Medium",
      "userType": "EMPLOYEE",
      "assignedRoles": [
        "R002",
        "R005"
      ],
      "lastLoginOn": "2026-06-30T08:12:00",
      "validFrom": "2022-03-01",
      "validTo": "9999-12-31",
      "employeeId": "100101",
      "plant": "Gurugram Plant",
      "designation": "AM"
    },
    {
      "userId": "U002",
      "userName": "averma",
      "firstName": "Anjali",
      "lastName": "Verma",
      "fullName": "Anjali Verma",
      "email": "anjali.verma@acme.com",
      "department": "Procurement",
      "jobTitle": "Purchasing Manager",
      "companyCode": "1000",
      "managerId": "U006",
      "managerName": "Vikram Chaudhary",
      "status": "Active",
      "riskLevel": "High",
      "userType": "EMPLOYEE",
      "assignedRoles": [
        "R001",
        "R003"
      ],
      "lastLoginOn": "2026-06-30T09:45:00",
      "validFrom": "2020-07-15",
      "validTo": "9999-12-31",
      "employeeId": "100102",
      "plant": "Manesar Plant",
      "designation": "MGR"
    },
    {
      "userId": "U003",
      "userName": "akumar",
      "firstName": "Amit",
      "lastName": "Kumar",
      "fullName": "Amit Kumar",
      "email": "amit.kumar@acme.com",
      "department": "DE-DCG",
      "jobTitle": "Security Administrator",
      "companyCode": "1000",
      "managerId": "U007",
      "managerName": "Kavita Mehra",
      "status": "Active",
      "riskLevel": "Low",
      "userType": "SECURITY",
      "assignedRoles": [
        "R007"
      ],
      "lastLoginOn": "2026-07-01T07:30:00",
      "validFrom": "2019-01-10",
      "validTo": "9999-12-31",
      "employeeId": "100103",
      "plant": "Gurugram Plant",
      "designation": "SMGR"
    },
    {
      "userId": "U004",
      "userName": "pmalhotra",
      "firstName": "Priya",
      "lastName": "Malhotra",
      "fullName": "Priya Malhotra",
      "email": "priya.malhotra@acme.com",
      "department": "Finance",
      "jobTitle": "Finance Manager",
      "companyCode": "1000",
      "managerId": null,
      "managerName": null,
      "status": "Active",
      "riskLevel": "Medium",
      "userType": "MANAGER",
      "assignedRoles": [
        "R002",
        "R004",
        "R006"
      ],
      "lastLoginOn": "2026-06-29T13:22:00",
      "validFrom": "2018-05-01",
      "validTo": "9999-12-31",
      "employeeId": "100104",
      "plant": "Gurugram Plant",
      "designation": "DPM"
    },
    {
      "userId": "U005",
      "userName": "ngupta",
      "firstName": "Neha",
      "lastName": "Gupta",
      "fullName": "Neha Gupta",
      "email": "neha.gupta@acme.com",
      "department": "Procurement",
      "jobTitle": "Buyer",
      "companyCode": "2000",
      "managerId": "U002",
      "managerName": "Anjali Verma",
      "status": "Active",
      "riskLevel": "High",
      "userType": "EMPLOYEE",
      "assignedRoles": [
        "R001",
        "R002"
      ],
      "lastLoginOn": "2026-06-28T15:10:00",
      "validFrom": "2021-09-20",
      "validTo": "9999-12-31",
      "employeeId": "100105",
      "plant": "Hansalpur Plant",
      "designation": "AM"
    },
    {
      "userId": "U006",
      "userName": "vchaudhary",
      "firstName": "Vikram",
      "lastName": "Chaudhary",
      "fullName": "Vikram Chaudhary",
      "email": "vikram.chaudhary@acme.com",
      "department": "Procurement",
      "jobTitle": "Head of Procurement",
      "companyCode": "1000",
      "managerId": null,
      "managerName": null,
      "status": "Active",
      "riskLevel": "Low",
      "userType": "MANAGER",
      "assignedRoles": [
        "R003"
      ],
      "lastLoginOn": "2026-06-30T10:05:00",
      "validFrom": "2015-02-01",
      "validTo": "9999-12-31",
      "employeeId": "100106",
      "plant": "Manesar Plant",
      "designation": "DPM"
    },
    {
      "userId": "U007",
      "userName": "kmehra",
      "firstName": "Kavita",
      "lastName": "Mehra",
      "fullName": "Kavita Mehra",
      "email": "kavita.mehra@acme.com",
      "department": "DE-DCG",
      "jobTitle": "DE-DCG Divisional Manager",
      "companyCode": "1000",
      "managerId": null,
      "managerName": null,
      "status": "Active",
      "riskLevel": "Low",
      "userType": "SECURITY",
      "assignedRoles": [
        "R008"
      ],
      "lastLoginOn": "2026-07-01T06:50:00",
      "validFrom": "2012-11-11",
      "validTo": "9999-12-31",
      "employeeId": "100107",
      "plant": "Gurugram Plant",
      "designation": "DVM"
    },
    {
      "userId": "U008",
      "userName": "tsingh",
      "firstName": "Tara",
      "lastName": "Singh",
      "fullName": "Tara Singh",
      "email": "tara.singh@acme.com",
      "department": "DE-DCG",
      "jobTitle": "Risk Officer",
      "companyCode": "1000",
      "managerId": "U007",
      "managerName": "Kavita Mehra",
      "status": "Active",
      "riskLevel": "Low",
      "userType": "SECURITY",
      "assignedRoles": [
        "R009"
      ],
      "lastLoginOn": "2026-06-30T16:40:00",
      "validFrom": "2017-04-03",
      "validTo": "9999-12-31",
      "employeeId": "100108",
      "plant": "Gurugram Plant",
      "designation": "MGR"
    },
    {
      "userId": "U009",
      "userName": "rkapoor",
      "firstName": "Rahul",
      "lastName": "Kapoor",
      "fullName": "Rahul Kapoor",
      "email": "rahul.kapoor@acme.com",
      "department": "Finance",
      "jobTitle": "GL Accountant",
      "companyCode": "1000",
      "managerId": "U004",
      "managerName": "Priya Malhotra",
      "status": "Locked",
      "riskLevel": "Medium",
      "userType": "EMPLOYEE",
      "assignedRoles": [
        "R004"
      ],
      "lastLoginOn": "2026-06-15T11:00:00",
      "validFrom": "2023-01-16",
      "validTo": "9999-12-31",
      "employeeId": "100109",
      "plant": "Gurugram Plant",
      "designation": "Probation"
    },
    {
      "userId": "U010",
      "userName": "svc_batch01",
      "firstName": "Batch",
      "lastName": "Service",
      "fullName": "Batch Service Account",
      "email": "noreply@acme.com",
      "department": "IT",
      "jobTitle": "System Account",
      "companyCode": "1000",
      "managerId": "U003",
      "managerName": "Amit Kumar",
      "status": "Active",
      "riskLevel": "High",
      "userType": "EMPLOYEE",
      "assignedRoles": [
        "R005",
        "R006"
      ],
      "lastLoginOn": "2026-07-01T03:00:00",
      "validFrom": "2020-01-01",
      "validTo": "9999-12-31",
      "employeeId": null,
      "plant": "Gurugram Plant",
      "designation": null
    }
  ]
}